Metadata-Version: 2.1
Name: teteLIB
Version: 0.1
Summary: TEST2
Author: TETE
License: MIT
Keywords: SOME,MEANINGFULL,KEYWORDS
License-File: LICENSE.txt
